{"nethernal":{"width":16,"height":18,"show":true},"neophyte":{"width":11,"height":20,"show":true},"taillesswretch":{"width":12,"height":20,"show":true},"taillessdruid":{"width":11,"height":20,"show":true},"caller":{"width":12,"height":20,"show":true},"mutatedpig":{"width":16,"height":20,"show":true},"blackbull":{"width":19,"height":16,"show":true},"taillesshorror":{"width":20,"height":13,"show":true},"parasite":{"width":20,"height":14,"show":true},"channeller":{"width":16,"height":16,"show":true},"apostle":{"width":14,"height":20,"show":true},"zealot":{"width":12,"height":20,"show":true},"protector":{"width":12,"height":20,"show":true},"redemptor":{"width":11,"height":20,"show":true},"brewer":{"width":9,"height":20,"show":true},"mutatedsheep":{"width":16,"height":18,"show":true},"fakeseat":{"width":20,"height":6,"show":true},"disciple":{"width":15,"height":20,"show":true},"fanatic":{"width":15,"height":20,"show":true},"hexer":{"width":16,"height":20,"show":true},"mirage":{"width":16,"height":16,"show":true},"skeletonvillagerminion":{"width":16,"height":19,"show":true},"vizier":{"width":16,"height":17,"show":true},"irk":{"width":16,"height":16,"show":true},"bullet":{"width":20,"height":14,"show":true}}